{
  "data": [
    {
      "id": "cj-17218745",
      "storeId": 7582444,
      "storeName": "Bc Babycare",
      "storeSlug": "bc-babycare",
      "title": "[Affiliate Only] Diaper 15% OFF with code:DIAPERAF2026",
      "description": "Bc Babycare Cloud Skin Diaper 15% OFF with code:DIAPERAF2026",
      "code": "DIAPERAF2026",
      "discount": "",
      "type": "percentage",
      "categories": [
        "Children"
      ],
      "expiryDate": "2026-06-30 16:00:00.0",
      "verified": true,
      "successRate": 0,
      "cjLink": "https://www.anrdoezrs.net/click-7977566-7582444?sid=s7582444_d17218745_mqf0hyxa_gx611m&url=https%3A%2F%2Fwww.bcbabycare.com%2Fproducts%2Fcloud-skin-diaper"
    },
    {
      "id": "cj-17148772",
      "storeId": 7636568,
      "storeName": "Coofandy",
      "storeSlug": "coofandy",
      "title": "Coofandy 15% OFF with code COOFANDY15",
      "description": "15% OFF Whole Site!",
      "code": "COOFANDY15",
      "discount": "",
      "type": "percentage",
      "categories": [
        "Mens"
      ],
      "expiryDate": "2026-08-27 16:00:00.0",
      "verified": true,
      "successRate": 0,
      "cjLink": "https://www.anrdoezrs.net/click-7977566-7636568?sid=s7636568_d17148772_mqf0hyxa_4f000o&url=https%3A%2F%2Fcoofandy.com%2F"
    },
    {
      "id": "cj-17190030",
      "storeId": 7686542,
      "storeName": "KSP Performance",
      "storeSlug": "ksp-performance",
      "title": "5% OFF KSP Performance Whole SIte with code: KSPAF",
      "description": "Code: KSPAF Automotive Parts for car and truck with 5% OFF site-wide",
      "code": "KSPAF",
      "discount": "",
      "type": "percentage",
      "categories": [
        "Parts & Accessories"
      ],
      "expiryDate": "2026-12-31 15:59:00.0",
      "verified": true,
      "successRate": 0,
      "cjLink": "https://www.anrdoezrs.net/click-7977566-7686542?sid=s7686542_d17190030_mqf0hyxa_pt9931&url=https%3A%2F%2Fwww.kspmotor.com%2F"
    }
  ],
  "timestamp": 1781515781902
}