{
  "data": [
    {
      "id": "cj-15736575",
      "storeId": 6404897,
      "storeName": "Aiper",
      "storeSlug": "aiper",
      "title": "Evergreen Link for Aiper",
      "description": "Evergreen Links are a long-lasting link type that takes consumers to the advertiser's website. It is deep-link enabled, so publishers can customize it to navigate to a different page if needed.",
      "discount": "",
      "discountType": "percentage",
      "categories": [
        "Garden"
      ],
      "cjLink": "https://www.anrdoezrs.net/click-101768918-15736575?sid=s6404897_d15736575_mqnhy2o6_g6jx1c",
      "startDate": "",
      "endDate": "",
      "featured": false
    },
    {
      "id": "cj-17200607",
      "storeId": 6404897,
      "storeName": "Aiper",
      "storeSlug": "aiper",
      "title": "2025 Black Friday US",
      "description": "160*600",
      "discount": "",
      "discountType": "percentage",
      "categories": [
        "Garden"
      ],
      "cjLink": "https://www.jdoqocy.com/click-101768918-17200607-1763482404000?sid=s6404897_d17200607_mqnhy2o6_t9eje7",
      "startDate": "",
      "endDate": "",
      "featured": false
    },
    {
      "id": "cj-17218623",
      "storeId": 6404897,
      "storeName": "Aiper",
      "storeSlug": "aiper",
      "title": "Aiper US",
      "description": "https://aiper.store/us/store",
      "discount": "",
      "discountType": "percentage",
      "categories": [
        "Garden"
      ],
      "cjLink": "https://www.dpbolvw.net/click-101768918-17218623-1765796020000?sid=s6404897_d17218623_mqnhy2o6_cs5hm2",
      "startDate": "",
      "endDate": "",
      "featured": false
    },
    {
      "id": "cj-17279495",
      "storeId": 6404897,
      "storeName": "Aiper",
      "storeSlug": "aiper",
      "title": "Mother's Day Sale",
      "description": "120*600",
      "discount": "",
      "discountType": "percentage",
      "categories": [
        "Garden"
      ],
      "cjLink": "https://www.dpbolvw.net/click-101768918-17279495-1776784059000?sid=s6404897_d17279495_mqnhy2o6_iwrnb2",
      "startDate": "",
      "endDate": "",
      "featured": false
    },
    {
      "id": "cj-17200608",
      "storeId": 6404897,
      "storeName": "Aiper",
      "storeSlug": "aiper",
      "title": "2025 Black Friday US",
      "description": "300*250",
      "discount": "",
      "discountType": "percentage",
      "categories": [
        "Garden"
      ],
      "cjLink": "https://www.dpbolvw.net/click-101768918-17200608-1763476786000?sid=s6404897_d17200608_mqnhy2o6_f9imze",
      "startDate": "",
      "endDate": "",
      "featured": false
    },
    {
      "id": "cj-17200651",
      "storeId": 6404897,
      "storeName": "Aiper",
      "storeSlug": "aiper",
      "title": "2025 Black Friday US",
      "description": "468*90",
      "discount": "",
      "discountType": "percentage",
      "categories": [
        "Garden"
      ],
      "cjLink": "https://www.dpbolvw.net/click-101768918-17200651-1763482226000?sid=s6404897_d17200651_mqnhy2o6_xp7le0",
      "startDate": "",
      "endDate": "",
      "featured": false
    },
    {
      "id": "cj-17200606",
      "storeId": 6404897,
      "storeName": "Aiper",
      "storeSlug": "aiper",
      "title": "2025 Black Friday US",
      "description": "120*600",
      "discount": "",
      "discountType": "percentage",
      "categories": [
        "Garden"
      ],
      "cjLink": "https://www.kqzyfj.com/click-101768918-17200606-1763482424000?sid=s6404897_d17200606_mqnhy2o6_tu3cas",
      "startDate": "",
      "endDate": "",
      "featured": false
    },
    {
      "id": "cj-17279509",
      "storeId": 6404897,
      "storeName": "Aiper",
      "storeSlug": "aiper",
      "title": "Mother's Day Sale",
      "description": "1200*1200",
      "discount": "",
      "discountType": "percentage",
      "categories": [
        "Garden"
      ],
      "cjLink": "https://www.jdoqocy.com/click-101768918-17279509-1776784385000?sid=s6404897_d17279509_mqnhy2o6_iit4u6",
      "startDate": "",
      "endDate": "",
      "featured": false
    },
    {
      "id": "cj-17200652",
      "storeId": 6404897,
      "storeName": "Aiper",
      "storeSlug": "aiper",
      "title": "2025 Black Friday US",
      "description": "728*90",
      "discount": "",
      "discountType": "percentage",
      "categories": [
        "Garden"
      ],
      "cjLink": "https://www.anrdoezrs.net/click-101768918-17200652-1763482381000?sid=s6404897_d17200652_mqnhy2o6_7cicpw",
      "startDate": "",
      "endDate": "",
      "featured": false
    },
    {
      "id": "cj-17262223",
      "storeId": 6404897,
      "storeName": "Aiper",
      "storeSlug": "aiper",
      "title": "Aiper Experts Duo",
      "description": "Save ＄200 at https://aiper.store/us/products/aiper-experts-duo",
      "discount": "",
      "discountType": "percentage",
      "categories": [
        "Garden"
      ],
      "cjLink": "https://www.dpbolvw.net/click-101768918-17262223-1773767571000?sid=s6404897_d17262223_mqnhy2o6_ekts48",
      "startDate": "",
      "endDate": "",
      "featured": false
    },
    {
      "id": "cj-17279502",
      "storeId": 6404897,
      "storeName": "Aiper",
      "storeSlug": "aiper",
      "title": "Mother's Day Sale",
      "description": "120*600",
      "discount": "",
      "discountType": "percentage",
      "categories": [
        "Garden"
      ],
      "cjLink": "https://www.kqzyfj.com/click-101768918-17279502-1776784278000?sid=s6404897_d17279502_mqnhy2o6_kz3vbf",
      "startDate": "",
      "endDate": "",
      "featured": false
    },
    {
      "id": "cj-17279504",
      "storeId": 6404897,
      "storeName": "Aiper",
      "storeSlug": "aiper",
      "title": "Mother's Day Sale",
      "description": "160*600",
      "discount": "",
      "discountType": "percentage",
      "categories": [
        "Garden"
      ],
      "cjLink": "https://www.jdoqocy.com/click-101768918-17279504-1776784313000?sid=s6404897_d17279504_mqnhy2o6_4rvu0h",
      "startDate": "",
      "endDate": "",
      "featured": false
    },
    {
      "id": "cj-17280042",
      "storeId": 7711902,
      "storeName": "AliExpress - Global",
      "storeSlug": "aliexpress-global",
      "title": "Brand day [Northern Hemisphere] 4.20-4.24",
      "description": "AliExpress Your Best Choice For Online Shopping.",
      "discount": "",
      "discountType": "percentage",
      "categories": [
        "E-commerce Solutions/Providers"
      ],
      "cjLink": "https://www.tkqlhce.com/click-101768918-17280042-1776855521000?sid=s7711902_d17280042_mqnhy2o6_itxkzp",
      "startDate": "",
      "endDate": "",
      "featured": false
    },
    {
      "id": "cj-17242061",
      "storeId": 7711902,
      "storeName": "AliExpress - Global",
      "storeSlug": "aliexpress-global",
      "title": "AliExpress Homepage (Global)",
      "description": "AliExpress Homepage (Global)",
      "discount": "",
      "discountType": "percentage",
      "categories": [
        "E-commerce Solutions/Providers"
      ],
      "cjLink": "https://www.kqzyfj.com/click-101768918-17242061-1773390959000?sid=s7711902_d17242061_mqnhy2o6_ey680u",
      "startDate": "",
      "endDate": "",
      "featured": false
    },
    {
      "id": "cj-17242115",
      "storeId": 7711902,
      "storeName": "AliExpress - Global",
      "storeSlug": "aliexpress-global",
      "title": "Better Choice on AliExpress",
      "description": "AliExpress Your Best Choice For Online Shopping. For Women, Men & Kids, Good Quality, Factory Price.",
      "discount": "",
      "discountType": "percentage",
      "categories": [
        "E-commerce Solutions/Providers"
      ],
      "cjLink": "https://www.kqzyfj.com/click-101768918-17242115-1770829683000?sid=s7711902_d17242115_mqnhy2o6_g6xr0o",
      "startDate": "",
      "endDate": "",
      "featured": false
    },
    {
      "id": "cj-17242063",
      "storeId": 7711902,
      "storeName": "AliExpress - Global",
      "storeSlug": "aliexpress-global",
      "title": "Home Furniture Category Products",
      "description": "Home Furniture Category Products Page",
      "discount": "",
      "discountType": "percentage",
      "categories": [
        "E-commerce Solutions/Providers"
      ],
      "cjLink": "https://www.jdoqocy.com/click-101768918-17242063-1770829684000?sid=s7711902_d17242063_mqnhy2o6_wi510w",
      "startDate": "",
      "endDate": "",
      "featured": false
    },
    {
      "id": "cj-17242069",
      "storeId": 7711902,
      "storeName": "AliExpress - Global",
      "storeSlug": "aliexpress-global",
      "title": "Automotive & Motocycle Category",
      "description": "Automotive & Motocycle category products page",
      "discount": "",
      "discountType": "percentage",
      "categories": [
        "E-commerce Solutions/Providers"
      ],
      "cjLink": "https://www.dpbolvw.net/click-101768918-17242069-1770829684000?sid=s7711902_d17242069_mqnhy2o6_dwdpta",
      "startDate": "",
      "endDate": "",
      "featured": false
    },
    {
      "id": "cj-17242108",
      "storeId": 7711902,
      "storeName": "AliExpress - Global",
      "storeSlug": "aliexpress-global",
      "title": "AliExpress Logo",
      "description": "AliExpress Your Best Choice For Online Shopping. For Women, Men & Kids, Good Quality, Factory Price.",
      "discount": "",
      "discountType": "percentage",
      "categories": [
        "E-commerce Solutions/Providers"
      ],
      "cjLink": "https://www.jdoqocy.com/click-101768918-17242108-1770829683000?sid=s7711902_d17242108_mqnhy2o6_jp1e89",
      "startDate": "",
      "endDate": "",
      "featured": false
    },
    {
      "id": "cj-17280048",
      "storeId": 7711902,
      "storeName": "AliExpress - Global",
      "storeSlug": "aliexpress-global",
      "title": "Mother's day [Northern Hemisphere] 4.26-4.28",
      "description": "AliExpress Your Best Choice For Online Shopping.",
      "discount": "",
      "discountType": "percentage",
      "categories": [
        "E-commerce Solutions/Providers"
      ],
      "cjLink": "https://www.tkqlhce.com/click-101768918-17280048-1776861417000?sid=s7711902_d17280048_mqnhy2o6_ujzxqp",
      "startDate": "",
      "endDate": "",
      "featured": false
    },
    {
      "id": "cj-17280046",
      "storeId": 7711902,
      "storeName": "AliExpress - Global",
      "storeSlug": "aliexpress-global",
      "title": "Mother's day [Southern Hemisphere] 4.26-4.28",
      "description": "AliExpress Your Best Choice For Online Shopping.",
      "discount": "",
      "discountType": "percentage",
      "categories": [
        "E-commerce Solutions/Providers"
      ],
      "cjLink": "https://www.dpbolvw.net/click-101768918-17280046-1776860765000?sid=s7711902_d17280046_mqnhy2o6_nx17zw",
      "startDate": "",
      "endDate": "",
      "featured": false
    },
    {
      "id": "cj-17294074",
      "storeId": 7711902,
      "storeName": "AliExpress - Global",
      "storeSlug": "aliexpress-global",
      "title": "May 23-31 AliExpress Mexico - Hot Sale Up to 90% off from",
      "description": "AliExpress Mexico Hot Sale",
      "discount": "",
      "discountType": "percentage",
      "categories": [
        "E-commerce Solutions/Providers"
      ],
      "cjLink": "https://www.tkqlhce.com/click-101768918-17294074-1779397843000?sid=s7711902_d17294074_mqnhy2o6_vttslo",
      "startDate": "",
      "endDate": "",
      "featured": false
    },
    {
      "id": "cj-17284532",
      "storeId": 7711902,
      "storeName": "AliExpress - Global",
      "storeSlug": "aliexpress-global",
      "title": "5.01-5.07 Summer Ready（BR）",
      "description": "AliExpress Your Best Choice For Online Shopping.",
      "discount": "",
      "discountType": "percentage",
      "categories": [
        "E-commerce Solutions/Providers"
      ],
      "cjLink": "https://www.kqzyfj.com/click-101768918-17284532-1777583896000?sid=s7711902_d17284532_mqnhy2o6_0r7k17",
      "startDate": "",
      "endDate": "",
      "featured": false
    },
    {
      "id": "cj-17242121",
      "storeId": 7711902,
      "storeName": "AliExpress - Global",
      "storeSlug": "aliexpress-global",
      "title": "AliExpress Homepage Banner",
      "description": "AliExpress Your Best Choice For Online Shopping. For Women, Men & Kids, Good Quality, Factory Price.",
      "discount": "",
      "discountType": "percentage",
      "categories": [
        "E-commerce Solutions/Providers"
      ],
      "cjLink": "https://www.tkqlhce.com/click-101768918-17242121-1770829682000?sid=s7711902_d17242121_mqnhy2o6_tnx1g4",
      "startDate": "",
      "endDate": "",
      "featured": false
    },
    {
      "id": "cj-17284529",
      "storeId": 7711902,
      "storeName": "AliExpress - Global",
      "storeSlug": "aliexpress-global",
      "title": "5.01-5.07 Summer Ready（US）",
      "description": "AliExpress Your Best Choice For Online Shopping.",
      "discount": "",
      "discountType": "percentage",
      "categories": [
        "E-commerce Solutions/Providers"
      ],
      "cjLink": "https://www.tkqlhce.com/click-101768918-17284529-1777583742000?sid=s7711902_d17284529_mqnhy2o6_xi1mjz",
      "startDate": "",
      "endDate": "",
      "featured": false
    },
    {
      "id": "cj-17288759",
      "storeId": 7711902,
      "storeName": "AliExpress - Global",
      "storeSlug": "aliexpress-global",
      "title": "5.11-5.15 Summer Refresh",
      "description": "AliExpress Your Best Choice For Online Shopping.",
      "discount": "",
      "discountType": "percentage",
      "categories": [
        "E-commerce Solutions/Providers"
      ],
      "cjLink": "https://www.dpbolvw.net/click-101768918-17288759-1778516652000?sid=s7711902_d17288759_mqnhy2o6_quzbrm",
      "startDate": "",
      "endDate": "",
      "featured": false
    },
    {
      "id": "cj-17288765",
      "storeId": 7711902,
      "storeName": "AliExpress - Global",
      "storeSlug": "aliexpress-global",
      "title": "5.11-5.15 Winter Refresh",
      "description": "AliExpress Your Best Choice For Online Shopping.",
      "discount": "",
      "discountType": "percentage",
      "categories": [
        "E-commerce Solutions/Providers"
      ],
      "cjLink": "https://www.tkqlhce.com/click-101768918-17288765-1778516826000?sid=s7711902_d17288765_mqnhy2o6_6jtwf4",
      "startDate": "",
      "endDate": "",
      "featured": false
    },
    {
      "id": "cj-17242118",
      "storeId": 7711902,
      "storeName": "AliExpress - Global",
      "storeSlug": "aliexpress-global",
      "title": "Local Shipping Up to 70% OFF",
      "description": "Local shipping up to 70% OFF",
      "discount": "",
      "discountType": "percentage",
      "categories": [
        "E-commerce Solutions/Providers"
      ],
      "cjLink": "https://www.kqzyfj.com/click-101768918-17242118-1770829682000?sid=s7711902_d17242118_mqnhy2o6_e0mf0d",
      "startDate": "",
      "endDate": "",
      "featured": false
    },
    {
      "id": "cj-17242131",
      "storeId": 7711902,
      "storeName": "AliExpress - Global",
      "storeSlug": "aliexpress-global",
      "title": "Clearance Items Up to 90% OFF",
      "description": "Last chance for clearance, up to 90% OFF",
      "discount": "",
      "discountType": "percentage",
      "categories": [
        "E-commerce Solutions/Providers"
      ],
      "cjLink": "https://www.kqzyfj.com/click-101768918-17242131-1770829681000?sid=s7711902_d17242131_mqnhy2o6_ue4gtu",
      "startDate": "",
      "endDate": "",
      "featured": false
    },
    {
      "id": "cj-17280043",
      "storeId": 7711902,
      "storeName": "AliExpress - Global",
      "storeSlug": "aliexpress-global",
      "title": "Brand day [Southern Hemisphere] 4.20-4.24",
      "description": "AliExpress Your Best Choice For Online Shopping.",
      "discount": "",
      "discountType": "percentage",
      "categories": [
        "E-commerce Solutions/Providers"
      ],
      "cjLink": "https://www.kqzyfj.com/click-101768918-17280043-1776855674000?sid=s7711902_d17280043_mqnhy2o6_st2kt6",
      "startDate": "",
      "endDate": "",
      "featured": false
    },
    {
      "id": "cj-17291907",
      "storeId": 7711902,
      "storeName": "AliExpress - Global",
      "storeSlug": "aliexpress-global",
      "title": "5.18-5.22 Sunshine Savings",
      "description": "AliExpress Homepage (Global)",
      "discount": "",
      "discountType": "percentage",
      "categories": [
        "E-commerce Solutions/Providers"
      ],
      "cjLink": "https://www.anrdoezrs.net/click-101768918-17291907-1779122523000?sid=s7711902_d17291907_mqnhy2o6_a5ssz0",
      "startDate": "",
      "endDate": "",
      "featured": false
    },
    {
      "id": "cj-17306560",
      "storeId": 7711902,
      "storeName": "AliExpress - Global",
      "storeSlug": "aliexpress-global",
      "title": "06.16-06.24[US]Mega Mid Year Sale UP to 80% OFF",
      "description": "6.16-6.24 Mega Mid Year Sale Up to 80% OFF",
      "discount": "",
      "discountType": "percentage",
      "categories": [
        "E-commerce Solutions/Providers"
      ],
      "cjLink": "https://www.anrdoezrs.net/click-101768918-17306560-1781613559000?sid=s7711902_d17306560_mqnhy2o6_2w6z7r",
      "startDate": "2026-06-15 16:00:00.0",
      "endDate": "2026-06-24 15:59:00.0",
      "featured": false
    },
    {
      "id": "cj-17284523",
      "storeId": 7711902,
      "storeName": "AliExpress - Global",
      "storeSlug": "aliexpress-global",
      "title": "5.01-5.07 Summer Ready（for ‌Global）",
      "description": "AliExpress Your Best Choice For Online Shopping.",
      "discount": "",
      "discountType": "percentage",
      "categories": [
        "E-commerce Solutions/Providers"
      ],
      "cjLink": "https://www.dpbolvw.net/click-101768918-17284523-1777583411000?sid=s7711902_d17284523_mqnhy2o6_n7elbw",
      "startDate": "",
      "endDate": "",
      "featured": false
    },
    {
      "id": "cj-17284527",
      "storeId": 7711902,
      "storeName": "AliExpress - Global",
      "storeSlug": "aliexpress-global",
      "title": "5.01-5.07 Summer Ready（for ‌Southern Hemisphere）",
      "description": "AliExpress Your Best Choice For Online Shopping.",
      "discount": "",
      "discountType": "percentage",
      "categories": [
        "E-commerce Solutions/Providers"
      ],
      "cjLink": "https://www.jdoqocy.com/click-101768918-17284527-1777583615000?sid=s7711902_d17284527_mqnhy2o6_hni238",
      "startDate": "",
      "endDate": "",
      "featured": false
    },
    {
      "id": "cj-17284524",
      "storeId": 7711902,
      "storeName": "AliExpress - Global",
      "storeSlug": "aliexpress-global",
      "title": "Mother's day [Northern Hemisphere] 4.26-4.28",
      "description": "AliExpress Your Best Choice For Online Shopping.",
      "discount": "",
      "discountType": "percentage",
      "categories": [
        "E-commerce Solutions/Providers"
      ],
      "cjLink": "https://www.tkqlhce.com/click-101768918-17284524-1777583438000?sid=s7711902_d17284524_mqnhy2o6_0i2mdz",
      "startDate": "",
      "endDate": "",
      "featured": false
    },
    {
      "id": "cj-17242065",
      "storeId": 7711902,
      "storeName": "AliExpress - Global",
      "storeSlug": "aliexpress-global",
      "title": "New user welcome deals up to 70% OFF",
      "description": "New user welcome deals up to 70% OFF",
      "discount": "",
      "discountType": "percentage",
      "categories": [
        "E-commerce Solutions/Providers"
      ],
      "cjLink": "https://www.kqzyfj.com/click-101768918-17242065-1770829684000?sid=s7711902_d17242065_mqnhy2o6_8jhfws",
      "startDate": "",
      "endDate": "",
      "featured": false
    },
    {
      "id": "cj-17242082",
      "storeId": 7711902,
      "storeName": "AliExpress - Global",
      "storeSlug": "aliexpress-global",
      "title": "Phone & Electronics Category",
      "description": "Phone & Electronics Category",
      "discount": "",
      "discountType": "percentage",
      "categories": [
        "E-commerce Solutions/Providers"
      ],
      "cjLink": "https://www.kqzyfj.com/click-101768918-17242082-1770829684000?sid=s7711902_d17242082_mqnhy2o6_nwqja3",
      "startDate": "",
      "endDate": "",
      "featured": false
    },
    {
      "id": "cj-17306566",
      "storeId": 7711902,
      "storeName": "AliExpress - Global",
      "storeSlug": "aliexpress-global",
      "title": "06.16-06.24[CL]Mega Mid Year Sale UP to 70% OFF",
      "description": "6.16-6.24 Mega Mid Year Sale for CL Up to 70% OFF",
      "discount": "",
      "discountType": "percentage",
      "categories": [
        "E-commerce Solutions/Providers"
      ],
      "cjLink": "https://www.tkqlhce.com/click-101768918-17306566-1781613917000?sid=s7711902_d17306566_mqnhy2o6_heacnb",
      "startDate": "2026-06-15 16:00:00.0",
      "endDate": "2026-06-24 15:59:00.0",
      "featured": false
    },
    {
      "id": "cj-17291909",
      "storeId": 7711902,
      "storeName": "AliExpress - Global",
      "storeSlug": "aliexpress-global",
      "title": "FR [Économies ensoleillées] Jusqu'à 60%",
      "description": "AliExpress Homepage (Global)",
      "discount": "",
      "discountType": "percentage",
      "categories": [
        "E-commerce Solutions/Providers"
      ],
      "cjLink": "https://www.dpbolvw.net/click-101768918-17291909-1779122670000?sid=s7711902_d17291909_mqnhy2o6_vb1xgh",
      "startDate": "",
      "endDate": "",
      "featured": false
    },
    {
      "id": "cj-17126173",
      "storeId": 7582444,
      "storeName": "Bc Babycare",
      "storeSlug": "bc-babycare",
      "title": "150x40",
      "description": "150x40",
      "discount": "",
      "discountType": "percentage",
      "categories": [
        "Children"
      ],
      "cjLink": "https://www.anrdoezrs.net/click-101768918-17126173-1780367453000?sid=s7582444_d17126173_mqnhy2o6_bixbp7",
      "startDate": "",
      "endDate": "",
      "featured": false
    },
    {
      "id": "cj-17126170",
      "storeId": 7582444,
      "storeName": "Bc Babycare",
      "storeSlug": "bc-babycare",
      "title": "Gyro VII Bottle Warmer",
      "description": "Gyro VII Bottle Warmer",
      "discount": "",
      "discountType": "percentage",
      "categories": [
        "Children"
      ],
      "cjLink": "https://www.anrdoezrs.net/click-101768918-17126170-1780367454000?sid=s7582444_d17126170_mqnhy2o6_f5w84n",
      "startDate": "",
      "endDate": "",
      "featured": false
    },
    {
      "id": "cj-17183962",
      "storeId": 7582444,
      "storeName": "Bc Babycare",
      "storeSlug": "bc-babycare",
      "title": "Hexa Effortless Carrier",
      "description": "Hexa Effortless Carrier",
      "discount": "",
      "discountType": "percentage",
      "categories": [
        "Children"
      ],
      "cjLink": "https://www.anrdoezrs.net/click-101768918-17183962-1780367452000?sid=s7582444_d17183962_mqnhy2o6_6ir45t",
      "startDate": "",
      "endDate": "",
      "featured": false
    },
    {
      "id": "cj-17183964",
      "storeId": 7582444,
      "storeName": "Bc Babycare",
      "storeSlug": "bc-babycare",
      "title": "Dino Barron Playpen",
      "description": "Dino Barron Playpen",
      "discount": "",
      "discountType": "percentage",
      "categories": [
        "Children"
      ],
      "cjLink": "https://www.tkqlhce.com/click-101768918-17183964-1780367452000?sid=s7582444_d17183964_mqnhy2o6_v3v1gc",
      "startDate": "",
      "endDate": "",
      "featured": false
    },
    {
      "id": "cj-17183963",
      "storeId": 7582444,
      "storeName": "Bc Babycare",
      "storeSlug": "bc-babycare",
      "title": "Tilted Anti-Spill Sippy Cup",
      "description": "Tilted Anti-Spill Sippy Cup",
      "discount": "",
      "discountType": "percentage",
      "categories": [
        "Children"
      ],
      "cjLink": "https://www.anrdoezrs.net/click-101768918-17183963-1780367452000?sid=s7582444_d17183963_mqnhy2o6_0fza59",
      "startDate": "",
      "endDate": "",
      "featured": false
    },
    {
      "id": "cj-17126171",
      "storeId": 7582444,
      "storeName": "Bc Babycare",
      "storeSlug": "bc-babycare",
      "title": "150x40",
      "description": "150x40",
      "discount": "",
      "discountType": "percentage",
      "categories": [
        "Children"
      ],
      "cjLink": "https://www.dpbolvw.net/click-101768918-17126171-1780367454000?sid=s7582444_d17126171_mqnhy2o6_aycbqj",
      "startDate": "",
      "endDate": "",
      "featured": false
    },
    {
      "id": "cj-17126166",
      "storeId": 7582444,
      "storeName": "Bc Babycare",
      "storeSlug": "bc-babycare",
      "title": "Baby Food Processor",
      "description": "Baby Food Processor",
      "discount": "",
      "discountType": "percentage",
      "categories": [
        "Children"
      ],
      "cjLink": "https://www.jdoqocy.com/click-101768918-17126166-1780367454000?sid=s7582444_d17126166_mqnhy2o6_3b6rou",
      "startDate": "",
      "endDate": "",
      "featured": false
    },
    {
      "id": "cj-17126165",
      "storeId": 7582444,
      "storeName": "Bc Babycare",
      "storeSlug": "bc-babycare",
      "title": "Mystery Box",
      "description": "Mystery Box",
      "discount": "",
      "discountType": "percentage",
      "categories": [
        "Children"
      ],
      "cjLink": "https://www.jdoqocy.com/click-101768918-17126165-1780367454000?sid=s7582444_d17126165_mqnhy2o6_fq2ha4",
      "startDate": "",
      "endDate": "",
      "featured": false
    },
    {
      "id": "cj-17126161",
      "storeId": 7582444,
      "storeName": "Bc Babycare",
      "storeSlug": "bc-babycare",
      "title": "Bc babycare Homepage",
      "description": "Back to school",
      "discount": "",
      "discountType": "percentage",
      "categories": [
        "Children"
      ],
      "cjLink": "https://www.anrdoezrs.net/click-101768918-17126161-1780367456000?sid=s7582444_d17126161_mqnhy2o6_pah486",
      "startDate": "",
      "endDate": "",
      "featured": false
    },
    {
      "id": "cj-17126168",
      "storeId": 7582444,
      "storeName": "Bc Babycare",
      "storeSlug": "bc-babycare",
      "title": "Portable Water and Milk Warmer",
      "description": "Portable Water and Milk Warmer",
      "discount": "",
      "discountType": "percentage",
      "categories": [
        "Children"
      ],
      "cjLink": "https://www.tkqlhce.com/click-101768918-17126168-1780367454000?sid=s7582444_d17126168_mqnhy2o6_4pvtis",
      "startDate": "",
      "endDate": "",
      "featured": false
    },
    {
      "id": "cj-17143842",
      "storeId": 7582444,
      "storeName": "Bc Babycare",
      "storeSlug": "bc-babycare",
      "title": "Evergreen Link for Bc Babycare",
      "description": "Evergreen Links are a long-lasting link type that takes consumers to the advertiser's website. It is deep-link enabled, so publishers can customize it to navigate to a different page if needed.",
      "discount": "",
      "discountType": "percentage",
      "categories": [
        "Children"
      ],
      "cjLink": "https://www.kqzyfj.com/click-101768918-17143842?sid=s7582444_d17143842_mqnhy2o6_t6hhsq",
      "startDate": "",
      "endDate": "",
      "featured": false
    },
    {
      "id": "cj-17183961",
      "storeId": 7582444,
      "storeName": "Bc Babycare",
      "storeSlug": "bc-babycare",
      "title": "CocoonGo Baby Carrier",
      "description": "CocoonGo Baby Carrier",
      "discount": "",
      "discountType": "percentage",
      "categories": [
        "Children"
      ],
      "cjLink": "https://www.dpbolvw.net/click-101768918-17183961-1780367452000?sid=s7582444_d17183961_mqnhy2o6_cntv1f",
      "startDate": "",
      "endDate": "",
      "featured": false
    },
    {
      "id": "cj-17059534",
      "storeId": 6536042,
      "storeName": "Chow Sang Sang",
      "storeSlug": "chow-sang-sang",
      "title": "200x175 Logo",
      "description": "Homepage",
      "discount": "",
      "discountType": "percentage",
      "categories": [
        "Jewelry"
      ],
      "cjLink": "https://www.anrdoezrs.net/click-101768918-17059534-1780506240000?sid=s6536042_d17059534_mqnhy2o6_4gehde",
      "startDate": "",
      "endDate": "",
      "featured": false
    },
    {
      "id": "cj-17067688",
      "storeId": 6536042,
      "storeName": "Chow Sang Sang",
      "storeSlug": "chow-sang-sang",
      "title": "額外1.5%即時回贈",
      "description": "額外1.5%即時回贈(Alipay HK﹑支付寶﹑WeChat Pay HK﹑ 微信支付或轉數快尊享)，受條款約束。",
      "discount": "",
      "discountType": "percentage",
      "categories": [
        "Jewelry"
      ],
      "cjLink": "https://www.kqzyfj.com/click-101768918-17067688-1780506240000?sid=s6536042_d17067688_mqnhy2o6_w951zx",
      "startDate": "",
      "endDate": "",
      "featured": false
    },
    {
      "id": "cj-17259241",
      "storeId": 6536042,
      "storeName": "Chow Sang Sang",
      "storeSlug": "chow-sang-sang",
      "title": "The Lightness of Feathers",
      "description": "Captures the beauty of movement, allowing every woman to feel the freedom of expression.",
      "discount": "",
      "discountType": "percentage",
      "categories": [
        "Jewelry"
      ],
      "cjLink": "https://www.anrdoezrs.net/click-101768918-17259241-1780506229000?sid=s6536042_d17259241_mqnhy2o6_u13yiy",
      "startDate": "",
      "endDate": "",
      "featured": false
    },
    {
      "id": "cj-17273203",
      "storeId": 6536042,
      "storeName": "Chow Sang Sang",
      "storeSlug": "chow-sang-sang",
      "title": "Seletected charms up to 30% off",
      "description": "Seletected charms up to 30% off. 1 free charm cord for every 2 charms purchase. Free shipping upon HK$3,900 purchase.",
      "discount": "",
      "discountType": "percentage",
      "categories": [
        "Jewelry"
      ],
      "cjLink": "https://www.tkqlhce.com/click-101768918-17273203-1780506225000?sid=s6536042_d17273203_mqnhy2o6_yx71u2",
      "startDate": "",
      "endDate": "",
      "featured": false
    },
    {
      "id": "cj-17273209",
      "storeId": 6536042,
      "storeName": "Chow Sang Sang",
      "storeSlug": "chow-sang-sang",
      "title": "Seletected charms up to 30% off",
      "description": "Seletected charms up to 30% off. 1 free charm cord for every 2 charms purchase. Free shipping upon HK$3,900 purchase.",
      "discount": "",
      "discountType": "percentage",
      "categories": [
        "Jewelry"
      ],
      "cjLink": "https://www.tkqlhce.com/click-101768918-17273209-1780506225000?sid=s6536042_d17273209_mqnhy2o6_r14sub",
      "startDate": "",
      "endDate": "",
      "featured": false
    },
    {
      "id": "cj-17273221",
      "storeId": 6536042,
      "storeName": "Chow Sang Sang",
      "storeSlug": "chow-sang-sang",
      "title": "Use code: HELLOGIFT",
      "description": "Receive a limited-edition Multi-functional storage container upon spending HK$2,000. Use code: HELLOGIFT",
      "discount": "",
      "discountType": "percentage",
      "categories": [
        "Jewelry"
      ],
      "cjLink": "https://www.anrdoezrs.net/click-101768918-17273221-1780506225000?sid=s6536042_d17273221_mqnhy2o6_h0f3ua",
      "startDate": "",
      "endDate": "",
      "featured": false
    },
    {
      "id": "cj-17273227",
      "storeId": 6536042,
      "storeName": "Chow Sang Sang",
      "storeSlug": "chow-sang-sang",
      "title": "Use code: HELLOGIFT",
      "description": "Receive a limited-edition Multi-functional storage container upon spending HK$2,000. Use code: HELLOGIFT",
      "discount": "",
      "discountType": "percentage",
      "categories": [
        "Jewelry"
      ],
      "cjLink": "https://www.dpbolvw.net/click-101768918-17273227-1780506224000?sid=s6536042_d17273227_mqnhy2o6_r4diae",
      "startDate": "",
      "endDate": "",
      "featured": false
    },
    {
      "id": "cj-17273233",
      "storeId": 6536042,
      "storeName": "Chow Sang Sang",
      "storeSlug": "chow-sang-sang",
      "title": "Gift Hello Kitty Bow Box. Promo code BOWBOX. *Not include gold ingot.",
      "description": "Purchase 1 Hello Kitty jewellery + 1 Sanrio characters jewellery to receive a gift Hello Kitty Bow Box. Promo code BOWBOX. *Not include gold ingot.",
      "discount": "",
      "discountType": "percentage",
      "categories": [
        "Jewelry"
      ],
      "cjLink": "https://www.anrdoezrs.net/click-101768918-17273233-1780506224000?sid=s6536042_d17273233_mqnhy2o6_jrkqkl",
      "startDate": "",
      "endDate": "",
      "featured": false
    },
    {
      "id": "cj-17303631",
      "storeId": 6536042,
      "storeName": "Chow Sang Sang",
      "storeSlug": "chow-sang-sang",
      "title": "6.9 Eternal Glow: Enjoy up to 12% off upon purchasing 2 fixed-price items, also enjoy 3% off selected jewellery for 2 price-by-weight items.Online Exclusive. Validity: 9 Jun (noon) - 23 Jun, 2026(HKT)",
      "description": "Chow Sang Sang eShop creates everlasting jewellery for every genuine love story. Enjoy up to 12% off upon purchasing 2 fixed-price items, also enjoy 3% off selected jewellery for 2 price-by-weight items. Online Exclusive. Validity: 9 Jun (noon) - 23 Jun, 2026(HKT)",
      "discount": "",
      "discountType": "percentage",
      "categories": [
        "Jewelry"
      ],
      "cjLink": "https://www.anrdoezrs.net/click-101768918-17303631-1781085357000?sid=s6536042_d17303631_mqnhy2o6_0ef450",
      "startDate": "",
      "endDate": "",
      "featured": false
    },
    {
      "id": "cj-17303628",
      "storeId": 6536042,
      "storeName": "Chow Sang Sang",
      "storeSlug": "chow-sang-sang",
      "title": "6.9 Eternal Glow: Enjoy up to 12% off upon purchasing 2 fixed-price items, also enjoy 3% off selected jewellery for 2 price-by-weight items.Online Exclusive. Validity: 9 Jun (noon) - 23 Jun, 2026(HKT)",
      "description": "Chow Sang Sang eShop creates everlasting jewellery for every genuine love story. Enjoy up to 12% off upon purchasing 2 fixed-price items, also enjoy 3% off selected jewellery for 2 price-by-weight items. Online Exclusive. Validity: 9 Jun (noon) - 23 Jun, 2026(HKT)",
      "discount": "",
      "discountType": "percentage",
      "categories": [
        "Jewelry"
      ],
      "cjLink": "https://www.dpbolvw.net/click-101768918-17303628-1781085356000?sid=s6536042_d17303628_mqnhy2o6_geop7v",
      "startDate": "",
      "endDate": "",
      "featured": false
    },
    {
      "id": "cj-17304350",
      "storeId": 6536042,
      "storeName": "Chow Sang Sang",
      "storeSlug": "chow-sang-sang",
      "title": "Gift Hello Kitty Bow Box. Not include gold ingot.",
      "description": "Purchase 1 Hello Kitty jewellery + 1 Sanrio characters jewellery to receive a gift Hello Kitty Bow Box. Not include gold ingot.",
      "discount": "",
      "discountType": "percentage",
      "categories": [
        "Jewelry"
      ],
      "cjLink": "https://www.anrdoezrs.net/click-101768918-17304350-1781190347000?sid=s6536042_d17304350_mqnhy2o6_nqfl4f",
      "startDate": "",
      "endDate": "",
      "featured": false
    },
    {
      "id": "cj-17304353",
      "storeId": 6536042,
      "storeName": "Chow Sang Sang",
      "storeSlug": "chow-sang-sang",
      "title": "Gift Hello Kitty Bow Box. Not include gold ingot.",
      "description": "Purchase 1 Hello Kitty jewellery + 1 Sanrio characters jewellery to receive a gift Hello Kitty Bow Box. Not include gold ingot.",
      "discount": "",
      "discountType": "percentage",
      "categories": [
        "Jewelry"
      ],
      "cjLink": "https://www.jdoqocy.com/click-101768918-17304353-1781190323000?sid=s6536042_d17304353_mqnhy2o6_vmthow",
      "startDate": "",
      "endDate": "",
      "featured": false
    },
    {
      "id": "cj-17304354",
      "storeId": 6536042,
      "storeName": "Chow Sang Sang",
      "storeSlug": "chow-sang-sang",
      "title": "Gift Hello Kitty Bow Box. Not include gold ingot.",
      "description": "Purchase 1 Hello Kitty jewellery + 1 Sanrio characters jewellery to receive a gift Hello Kitty Bow Box. Not include gold ingot.",
      "discount": "",
      "discountType": "percentage",
      "categories": [
        "Jewelry"
      ],
      "cjLink": "https://www.tkqlhce.com/click-101768918-17304354-1781190323000?sid=s6536042_d17304354_mqnhy2o6_nr2rny",
      "startDate": "",
      "endDate": "",
      "featured": false
    },
    {
      "id": "cj-17273240",
      "storeId": 6536042,
      "storeName": "Chow Sang Sang",
      "storeSlug": "chow-sang-sang",
      "title": "Gift Hello Kitty Bow Box. Promo code BOWBOX. *Not include gold ingot.",
      "description": "Purchase 1 Hello Kitty jewellery + 1 Sanrio characters jewellery to receive a gift Hello Kitty Bow Box. Promo code BOWBOX. *Not include gold ingot.",
      "discount": "",
      "discountType": "percentage",
      "categories": [
        "Jewelry"
      ],
      "cjLink": "https://www.kqzyfj.com/click-101768918-17273240-1780506224000?sid=s6536042_d17273240_mqnhy2o6_jwtnkw",
      "startDate": "",
      "endDate": "",
      "featured": false
    },
    {
      "id": "cj-17273246",
      "storeId": 6536042,
      "storeName": "Chow Sang Sang",
      "storeSlug": "chow-sang-sang",
      "title": "Gift Hello Kitty Bow Box. Promo code BOWBOX. *Not include gold ingot.",
      "description": "Purchase 1 Hello Kitty jewellery + 1 Sanrio characters jewellery to receive a gift Hello Kitty Bow Box. Promo code BOWBOX. *Not include gold ingot.",
      "discount": "",
      "discountType": "percentage",
      "categories": [
        "Jewelry"
      ],
      "cjLink": "https://www.tkqlhce.com/click-101768918-17273246-1780506223000?sid=s6536042_d17273246_mqnhy2o6_3ymhyl",
      "startDate": "",
      "endDate": "",
      "featured": false
    },
    {
      "id": "cj-17273226",
      "storeId": 6536042,
      "storeName": "Chow Sang Sang",
      "storeSlug": "chow-sang-sang",
      "title": "Use code: HELLOGIFT",
      "description": "Receive a limited-edition Multi-functional storage container upon spending HK$2,000. Use code: HELLOGIFT",
      "discount": "",
      "discountType": "percentage",
      "categories": [
        "Jewelry"
      ],
      "cjLink": "https://www.kqzyfj.com/click-101768918-17273226-1780506224000?sid=s6536042_d17273226_mqnhy2o6_7t2ye8",
      "startDate": "",
      "endDate": "",
      "featured": false
    },
    {
      "id": "cj-17273239",
      "storeId": 6536042,
      "storeName": "Chow Sang Sang",
      "storeSlug": "chow-sang-sang",
      "title": "Gift Hello Kitty Bow Box. Promo code BOWBOX. *Not include gold ingot.",
      "description": "Purchase 1 Hello Kitty jewellery + 1 Sanrio characters jewellery to receive a gift Hello Kitty Bow Box. Promo code BOWBOX. *Not include gold ingot.",
      "discount": "",
      "discountType": "percentage",
      "categories": [
        "Jewelry"
      ],
      "cjLink": "https://www.kqzyfj.com/click-101768918-17273239-1780506224000?sid=s6536042_d17273239_mqnhy2o6_2hlnm9",
      "startDate": "",
      "endDate": "",
      "featured": false
    },
    {
      "id": "cj-17273244",
      "storeId": 6536042,
      "storeName": "Chow Sang Sang",
      "storeSlug": "chow-sang-sang",
      "title": "Gift Hello Kitty Bow Box. Promo code BOWBOX. *Not include gold ingot.",
      "description": "Purchase 1 Hello Kitty jewellery + 1 Sanrio characters jewellery to receive a gift Hello Kitty Bow Box. Promo code BOWBOX. *Not include gold ingot.",
      "discount": "",
      "discountType": "percentage",
      "categories": [
        "Jewelry"
      ],
      "cjLink": "https://www.jdoqocy.com/click-101768918-17273244-1780506224000?sid=s6536042_d17273244_mqnhy2o6_zm0fiv",
      "startDate": "",
      "endDate": "",
      "featured": false
    },
    {
      "id": "cj-17273208",
      "storeId": 6536042,
      "storeName": "Chow Sang Sang",
      "storeSlug": "chow-sang-sang",
      "title": "Seletected charms up to 30% off",
      "description": "Seletected charms up to 30% off. 1 free charm cord for every 2 charms purchase. Free shipping upon HK$3,900 purchase.",
      "discount": "",
      "discountType": "percentage",
      "categories": [
        "Jewelry"
      ],
      "cjLink": "https://www.kqzyfj.com/click-101768918-17273208-1780506225000?sid=s6536042_d17273208_mqnhy2o6_tuf0cl",
      "startDate": "",
      "endDate": "",
      "featured": false
    },
    {
      "id": "cj-17273219",
      "storeId": 6536042,
      "storeName": "Chow Sang Sang",
      "storeSlug": "chow-sang-sang",
      "title": "Use code: HELLOGIFT",
      "description": "Receive a limited-edition Multi-functional storage container upon spending HK$2,000. Use code: HELLOGIFT",
      "discount": "",
      "discountType": "percentage",
      "categories": [
        "Jewelry"
      ],
      "cjLink": "https://www.tkqlhce.com/click-101768918-17273219-1780506224000?sid=s6536042_d17273219_mqnhy2o6_olrx9p",
      "startDate": "",
      "endDate": "",
      "featured": false
    },
    {
      "id": "cj-17273234",
      "storeId": 6536042,
      "storeName": "Chow Sang Sang",
      "storeSlug": "chow-sang-sang",
      "title": "Gift Hello Kitty Bow Box. Promo code BOWBOX. *Not include gold ingot.",
      "description": "Purchase 1 Hello Kitty jewellery + 1 Sanrio characters jewellery to receive a gift Hello Kitty Bow Box. Promo code BOWBOX. *Not include gold ingot.",
      "discount": "",
      "discountType": "percentage",
      "categories": [
        "Jewelry"
      ],
      "cjLink": "https://www.tkqlhce.com/click-101768918-17273234-1780506224000?sid=s6536042_d17273234_mqnhy2o6_r60ojm",
      "startDate": "",
      "endDate": "",
      "featured": false
    },
    {
      "id": "cj-17273190",
      "storeId": 6536042,
      "storeName": "Chow Sang Sang",
      "storeSlug": "chow-sang-sang",
      "title": "FTV offers_HKIP",
      "description": "FTV offers_HKIP: HK IP + MO IP: With inputting promo code FTV100EF, enjoy extra HK$100 off upon every HK$3,000 (Applicable to fixed price jewellery only) for the first time purchase. Terms apply",
      "discount": "",
      "discountType": "percentage",
      "categories": [
        "Jewelry"
      ],
      "cjLink": "https://www.tkqlhce.com/click-101768918-17273190-1780506225000?sid=s6536042_d17273190_mqnhy2o6_i591gn",
      "startDate": "",
      "endDate": "",
      "featured": false
    },
    {
      "id": "cj-17274607",
      "storeId": 6536042,
      "storeName": "Chow Sang Sang",
      "storeSlug": "chow-sang-sang",
      "title": "【Evergreen】Fixed price jewellery promotion",
      "description": "Purchase selected fixed price jewellery at Chow Sang Sang eShop and enjoy 10% off for 1 piece, 12% off for 2 pieces. Terms apply",
      "discount": "",
      "discountType": "percentage",
      "categories": [
        "Jewelry"
      ],
      "cjLink": "https://www.dpbolvw.net/click-101768918-17274607-1780506223000?sid=s6536042_d17274607_mqnhy2o6_tvq9c8",
      "startDate": "",
      "endDate": "",
      "featured": false
    },
    {
      "id": "cj-17274610",
      "storeId": 6536042,
      "storeName": "Chow Sang Sang",
      "storeSlug": "chow-sang-sang",
      "title": "【Evergreen】Fixed price jewellery promotion",
      "description": "Purchase selected fixed price jewellery at Chow Sang Sang eShop and enjoy 10% off for 1 piece, 12% off for 2 pieces. Terms apply",
      "discount": "",
      "discountType": "percentage",
      "categories": [
        "Jewelry"
      ],
      "cjLink": "https://www.kqzyfj.com/click-101768918-17274610-1780506223000?sid=s6536042_d17274610_mqnhy2o6_tqyu63",
      "startDate": "",
      "endDate": "",
      "featured": false
    },
    {
      "id": "cj-17274604",
      "storeId": 6536042,
      "storeName": "Chow Sang Sang",
      "storeSlug": "chow-sang-sang",
      "title": "【Evergreen】Fixed price jewellery promotion",
      "description": "Purchase selected fixed price jewellery at Chow Sang Sang eShop and enjoy 10% off for 1 piece, 12% off for 2 pieces. Terms apply",
      "discount": "",
      "discountType": "percentage",
      "categories": [
        "Jewelry"
      ],
      "cjLink": "https://www.tkqlhce.com/click-101768918-17274604-1780506223000?sid=s6536042_d17274604_mqnhy2o6_slypac",
      "startDate": "",
      "endDate": "",
      "featured": false
    },
    {
      "id": "cj-17274603",
      "storeId": 6536042,
      "storeName": "Chow Sang Sang",
      "storeSlug": "chow-sang-sang",
      "title": "【Evergreen】Selected fixed price jewellery promotion",
      "description": "Purchase selected fixed price jewellery at Chow Sang Sang eShop and enjoy 10% off for 1 piece, 12% off for 2 pieces. Terms apply",
      "discount": "",
      "discountType": "percentage",
      "categories": [
        "Jewelry"
      ],
      "cjLink": "https://www.anrdoezrs.net/click-101768918-17274603-1780506223000?sid=s6536042_d17274603_mqnhy2o6_2pg31s",
      "startDate": "",
      "endDate": "",
      "featured": false
    },
    {
      "id": "cj-17274608",
      "storeId": 6536042,
      "storeName": "Chow Sang Sang",
      "storeSlug": "chow-sang-sang",
      "title": "【Evergreen】Fixed price jewellery promotion",
      "description": "Purchase selected fixed price jewellery at Chow Sang Sang eShop and enjoy 10% off for 1 piece, 12% off for 2 pieces. Terms apply",
      "discount": "",
      "discountType": "percentage",
      "categories": [
        "Jewelry"
      ],
      "cjLink": "https://www.tkqlhce.com/click-101768918-17274608-1780506223000?sid=s6536042_d17274608_mqnhy2o6_7e7sir",
      "startDate": "",
      "endDate": "",
      "featured": false
    },
    {
      "id": "cj-17276175",
      "storeId": 6536042,
      "storeName": "Chow Sang Sang",
      "storeSlug": "chow-sang-sang",
      "title": "Get HK$150 off upon, every HK$4,000 purchase on gold jewellery. Promo code : GJA",
      "description": "Get HK$150 off upon, every HK$4,000 purchase on gold jewellery. Promo code : GJA\nPrices for UK orders already include local duties and taxes. Terms apply / Online exclusive",
      "discount": "",
      "discountType": "percentage",
      "categories": [
        "Jewelry"
      ],
      "cjLink": "https://www.dpbolvw.net/click-101768918-17276175-1780506222000?sid=s6536042_d17276175_mqnhy2o6_l2tsc7",
      "startDate": "",
      "endDate": "",
      "featured": false
    },
    {
      "id": "cj-17276182",
      "storeId": 6536042,
      "storeName": "Chow Sang Sang",
      "storeSlug": "chow-sang-sang",
      "title": "Get HK$150 off upon, every HK$4,000 purchase on gold jewellery. Promo code : GJA",
      "description": "Get HK$150 off upon, every HK$4,000 purchase on gold jewellery. Promo code : GJA\nPrices for UK orders already include local duties and taxes. Terms apply / Online exclusive",
      "discount": "",
      "discountType": "percentage",
      "categories": [
        "Jewelry"
      ],
      "cjLink": "https://www.kqzyfj.com/click-101768918-17276182-1780506221000?sid=s6536042_d17276182_mqnhy2o6_xqyw7s",
      "startDate": "",
      "endDate": "",
      "featured": false
    },
    {
      "id": "cj-17276180",
      "storeId": 6536042,
      "storeName": "Chow Sang Sang",
      "storeSlug": "chow-sang-sang",
      "title": "Get HK$150 off upon, every HK$4,000 purchase on gold jewellery. Promo code : GJA",
      "description": "Get HK$150 off upon, every HK$4,000 purchase on gold jewellery. Promo code : GJA\nPrices for UK orders already include local duties and taxes. Terms apply / Online exclusive",
      "discount": "",
      "discountType": "percentage",
      "categories": [
        "Jewelry"
      ],
      "cjLink": "https://www.tkqlhce.com/click-101768918-17276180-1780506221000?sid=s6536042_d17276180_mqnhy2o6_8hsygh",
      "startDate": "",
      "endDate": "",
      "featured": false
    },
    {
      "id": "cj-17299192",
      "storeId": 6536042,
      "storeName": "Chow Sang Sang",
      "storeSlug": "chow-sang-sang",
      "title": "Crafted to define strength",
      "description": "Crafted to define strength\nCrafted with Noir Artistry that accentuates layered textures and exquisitely renders intricate details.",
      "discount": "",
      "discountType": "percentage",
      "categories": [
        "Jewelry"
      ],
      "cjLink": "https://www.jdoqocy.com/click-101768918-17299192-1780506216000?sid=s6536042_d17299192_mqnhy2o6_6e658v",
      "startDate": "",
      "endDate": "",
      "featured": false
    },
    {
      "id": "cj-17067683",
      "storeId": 6536042,
      "storeName": "Chow Sang Sang",
      "storeSlug": "chow-sang-sang",
      "title": "指定薄荷系列飾品75折",
      "description": "指定薄荷系列飾品75折，香港、澳門地區免運費。全球指定30個國家可享HK$3,900免運費。",
      "discount": "",
      "discountType": "percentage",
      "categories": [
        "Jewelry"
      ],
      "cjLink": "https://www.tkqlhce.com/click-101768918-17067683-1780506240000?sid=s6536042_d17067683_mqnhy2o6_e12ek5",
      "startDate": "",
      "endDate": "",
      "featured": false
    },
    {
      "id": "cj-17289257",
      "storeId": 6536042,
      "storeName": "Chow Sang Sang",
      "storeSlug": "chow-sang-sang",
      "title": "Cultural Blessings",
      "description": "Cultural Blessings\nBlessings through the years",
      "discount": "",
      "discountType": "percentage",
      "categories": [
        "Jewelry"
      ],
      "cjLink": "https://www.jdoqocy.com/click-101768918-17289257-1780506219000?sid=s6536042_d17289257_mqnhy2o6_gajsmh",
      "startDate": "",
      "endDate": "",
      "featured": false
    },
    {
      "id": "cj-17289259",
      "storeId": 6536042,
      "storeName": "Chow Sang Sang",
      "storeSlug": "chow-sang-sang",
      "title": "charme my way",
      "description": "charme my way\nAdorable cat and dog motifs gold charms, a warm touch for every day.",
      "discount": "",
      "discountType": "percentage",
      "categories": [
        "Jewelry"
      ],
      "cjLink": "https://www.dpbolvw.net/click-101768918-17289259-1780506219000?sid=s6536042_d17289259_mqnhy2o6_p148bc",
      "startDate": "",
      "endDate": "",
      "featured": false
    },
    {
      "id": "cj-17289263",
      "storeId": 6536042,
      "storeName": "Chow Sang Sang",
      "storeSlug": "chow-sang-sang",
      "title": "Begin your journey with real gold—start small",
      "description": "Begin your journey with real gold—start small\nAvailable in 1g, 3g, 5g weights and three timeless forms – Auspicious coin, sycee pony or classic gold brick.",
      "discount": "",
      "discountType": "percentage",
      "categories": [
        "Jewelry"
      ],
      "cjLink": "https://www.jdoqocy.com/click-101768918-17289263-1780506219000?sid=s6536042_d17289263_mqnhy2o6_ce9nud",
      "startDate": "",
      "endDate": "",
      "featured": false
    },
    {
      "id": "cj-17303629",
      "storeId": 6536042,
      "storeName": "Chow Sang Sang",
      "storeSlug": "chow-sang-sang",
      "title": "6.9 Eternal Glow: Enjoy up to 12% off upon purchasing 2 fixed-price items, also enjoy 3% off selected jewellery for 2 price-by-weight items.Online Exclusive. Validity: 9 Jun (noon) - 23 Jun, 2026(HKT)",
      "description": "Chow Sang Sang eShop creates everlasting jewellery for every genuine love story. Enjoy up to 12% off upon purchasing 2 fixed-price items, also enjoy 3% off selected jewellery for 2 price-by-weight items. Online Exclusive. Validity: 9 Jun (noon) - 23 Jun, 2026(HKT)",
      "discount": "",
      "discountType": "percentage",
      "categories": [
        "Jewelry"
      ],
      "cjLink": "https://www.jdoqocy.com/click-101768918-17303629-1781085356000?sid=s6536042_d17303629_mqnhy2o7_s8ho9c",
      "startDate": "",
      "endDate": "",
      "featured": false
    },
    {
      "id": "cj-17303640",
      "storeId": 6536042,
      "storeName": "Chow Sang Sang",
      "storeSlug": "chow-sang-sang",
      "title": "6.9 Eternal Glow Biweekly promtoion",
      "description": "Chow Sang Sang eShop creates everlasting jewellery for every genuine love story. Enjoy up to 12% off upon purchasing 2 fixed-price items, also enjoy 3% off selected jewellery for 2 price-by-weight items. Online Exclusive. Validity: 9 Jun (noon) - 23 Jun, 2026(HKT)",
      "discount": "",
      "discountType": "percentage",
      "categories": [
        "Jewelry"
      ],
      "cjLink": "https://www.anrdoezrs.net/click-101768918-17303640-1781085403000?sid=s6536042_d17303640_mqnhy2o7_ityhen",
      "startDate": "",
      "endDate": "",
      "featured": false
    },
    {
      "id": "cj-17234752",
      "storeId": 6536042,
      "storeName": "Chow Sang Sang",
      "storeSlug": "chow-sang-sang",
      "title": "Selected fixed price jewellery promotion",
      "description": "Offer Details: Up to 30% off on selected fixed price jewellery",
      "discount": "",
      "discountType": "percentage",
      "categories": [
        "Jewelry"
      ],
      "cjLink": "https://www.anrdoezrs.net/click-101768918-17234752-1780506239000?sid=s6536042_d17234752_mqnhy2o7_bq8ltl",
      "startDate": "",
      "endDate": "",
      "featured": false
    },
    {
      "id": "cj-17273177",
      "storeId": 6536042,
      "storeName": "Chow Sang Sang",
      "storeSlug": "chow-sang-sang",
      "title": "FTV offers_OSIP",
      "description": "FTV offers_OSIP: Non HK IP + MO IP: With inputting promo code FTV100EA, enjoy extra HK$100 off upon every HK$3500 purchase for the first time purchase. Terms apply",
      "discount": "",
      "discountType": "percentage",
      "categories": [
        "Jewelry"
      ],
      "cjLink": "https://www.tkqlhce.com/click-101768918-17273177-1780506226000?sid=s6536042_d17273177_mqnhy2o7_xyk6a6",
      "startDate": "",
      "endDate": "",
      "featured": false
    },
    {
      "id": "cj-17273180",
      "storeId": 6536042,
      "storeName": "Chow Sang Sang",
      "storeSlug": "chow-sang-sang",
      "title": "FTV offers_OSIP",
      "description": "FTV offers_OSIP: Non HK IP + MO IP: With inputting promo code FTV100EA, enjoy extra HK$100 off upon every HK$3500 purchase for the first time purchase. Terms apply",
      "discount": "",
      "discountType": "percentage",
      "categories": [
        "Jewelry"
      ],
      "cjLink": "https://www.tkqlhce.com/click-101768918-17273180-1780506226000?sid=s6536042_d17273180_mqnhy2o7_jvozsc",
      "startDate": "",
      "endDate": "",
      "featured": false
    },
    {
      "id": "cj-17273183",
      "storeId": 6536042,
      "storeName": "Chow Sang Sang",
      "storeSlug": "chow-sang-sang",
      "title": "FTV offers_OSIP",
      "description": "FTV offers_OSIP: Non HK IP + MO IP: With inputting promo code FTV100EA, enjoy extra HK$100 off upon every HK$3500 purchase for the first time purchase. Terms apply",
      "discount": "",
      "discountType": "percentage",
      "categories": [
        "Jewelry"
      ],
      "cjLink": "https://www.jdoqocy.com/click-101768918-17273183-1780506226000?sid=s6536042_d17273183_mqnhy2o7_osbxb0",
      "startDate": "",
      "endDate": "",
      "featured": false
    },
    {
      "id": "cj-17273187",
      "storeId": 6536042,
      "storeName": "Chow Sang Sang",
      "storeSlug": "chow-sang-sang",
      "title": "FTV offers_HKIP: HK IP + MO IP: With inputting promo code FTV100EF, enjoy extra HK$100 off upon every HK$3,000 (Applicable to fixed price jewellery only) for the first time purchase. Terms apply",
      "description": "FTV offers_HKIP: HK IP + MO IP: With inputting promo code FTV100EF, enjoy extra HK$100 off upon every HK$3,000 (Applicable to fixed price jewellery only) for the first time purchase. Terms apply",
      "discount": "",
      "discountType": "percentage",
      "categories": [
        "Jewelry"
      ],
      "cjLink": "https://www.dpbolvw.net/click-101768918-17273187-1780506225000?sid=s6536042_d17273187_mqnhy2o7_a6tcoc",
      "startDate": "",
      "endDate": "",
      "featured": false
    },
    {
      "id": "cj-17273232",
      "storeId": 6536042,
      "storeName": "Chow Sang Sang",
      "storeSlug": "chow-sang-sang",
      "title": "Gift Hello Kitty Bow Box. Promo code BOWBOX. *Not include gold ingot.",
      "description": "Purchase 1 Hello Kitty jewellery + 1 Sanrio characters jewellery to receive a gift Hello Kitty Bow Box. Promo code BOWBOX. *Not include gold ingot.",
      "discount": "",
      "discountType": "percentage",
      "categories": [
        "Jewelry"
      ],
      "cjLink": "https://www.dpbolvw.net/click-101768918-17273232-1780506224000?sid=s6536042_d17273232_mqnhy2o7_g8v4me",
      "startDate": "",
      "endDate": "",
      "featured": false
    },
    {
      "id": "cj-17273235",
      "storeId": 6536042,
      "storeName": "Chow Sang Sang",
      "storeSlug": "chow-sang-sang",
      "title": "Gift Hello Kitty Bow Box. Promo code BOWBOX. *Not include gold ingot.",
      "description": "Purchase 1 Hello Kitty jewellery + 1 Sanrio characters jewellery to receive a gift Hello Kitty Bow Box. Promo code BOWBOX. *Not include gold ingot.",
      "discount": "",
      "discountType": "percentage",
      "categories": [
        "Jewelry"
      ],
      "cjLink": "https://www.tkqlhce.com/click-101768918-17273235-1780506224000?sid=s6536042_d17273235_mqnhy2o7_uuldyn",
      "startDate": "",
      "endDate": "",
      "featured": false
    },
    {
      "id": "cj-17273220",
      "storeId": 6536042,
      "storeName": "Chow Sang Sang",
      "storeSlug": "chow-sang-sang",
      "title": "Use code: HELLOGIFT",
      "description": "Receive a limited-edition Multi-functional storage container upon spending HK$2,000. Use code: HELLOGIFT",
      "discount": "",
      "discountType": "percentage",
      "categories": [
        "Jewelry"
      ],
      "cjLink": "https://www.anrdoezrs.net/click-101768918-17273220-1780506225000?sid=s6536042_d17273220_mqnhy2o7_r9puoq",
      "startDate": "",
      "endDate": "",
      "featured": false
    },
    {
      "id": "cj-17273192",
      "storeId": 6536042,
      "storeName": "Chow Sang Sang",
      "storeSlug": "chow-sang-sang",
      "title": "FTV offers_HKIP",
      "description": "FTV offers_HKIP: HK IP + MO IP: With inputting promo code FTV100EF, enjoy extra HK$100 off upon every HK$3,000 (Applicable to fixed price jewellery only) for the first time purchase. Terms apply",
      "discount": "",
      "discountType": "percentage",
      "categories": [
        "Jewelry"
      ],
      "cjLink": "https://www.dpbolvw.net/click-101768918-17273192-1780506225000?sid=s6536042_d17273192_mqnhy2o7_xufwtb",
      "startDate": "",
      "endDate": "",
      "featured": false
    },
    {
      "id": "cj-17273199",
      "storeId": 6536042,
      "storeName": "Chow Sang Sang",
      "storeSlug": "chow-sang-sang",
      "title": "FTV offers_HKIP",
      "description": "FTV offers_HKIP: HK IP + MO IP: With inputting promo code FTV100EF, enjoy extra HK$100 off upon every HK$3,000 (Applicable to fixed price jewellery only) for the first time purchase. Terms apply",
      "discount": "",
      "discountType": "percentage",
      "categories": [
        "Jewelry"
      ],
      "cjLink": "https://www.kqzyfj.com/click-101768918-17273199-1780506225000?sid=s6536042_d17273199_mqnhy2o7_r5ja2u",
      "startDate": "",
      "endDate": "",
      "featured": false
    },
    {
      "id": "cj-17273202",
      "storeId": 6536042,
      "storeName": "Chow Sang Sang",
      "storeSlug": "chow-sang-sang",
      "title": "Seletected charms up to 30% off",
      "description": "Seletected charms up to 30% off. 1 free charm cord for every 2 charms purchase. Free shipping upon HK$3,900 purchase.",
      "discount": "",
      "discountType": "percentage",
      "categories": [
        "Jewelry"
      ],
      "cjLink": "https://www.jdoqocy.com/click-101768918-17273202-1780506225000?sid=s6536042_d17273202_mqnhy2o7_1qj61x",
      "startDate": "",
      "endDate": "",
      "featured": false
    },
    {
      "id": "cj-17273178",
      "storeId": 6536042,
      "storeName": "Chow Sang Sang",
      "storeSlug": "chow-sang-sang",
      "title": "FTV offers_OSIP",
      "description": "FTV offers_OSIP: Non HK IP + MO IP: With inputting promo code FTV100EA, enjoy extra HK$100 off upon every HK$3500 purchase for the first time purchase. Terms apply",
      "discount": "",
      "discountType": "percentage",
      "categories": [
        "Jewelry"
      ],
      "cjLink": "https://www.kqzyfj.com/click-101768918-17273178-1780506226000?sid=s6536042_d17273178_mqnhy2o7_spjrrp",
      "startDate": "",
      "endDate": "",
      "featured": false
    }
  ],
  "timestamp": 1782028816135
}